scrapxd/__init__.py
scrapxd/analytics.py
scrapxd/client.py
scrapxd/config.py
scrapxd/export.py
scrapxd/fetcher.py
scrapxd/models/__init__.py
scrapxd/models/base.py
scrapxd/models/entry.py
scrapxd/models/entry_list.py
scrapxd/models/film.py
scrapxd/models/film_list.py
scrapxd/models/film_search.py
scrapxd/models/user.py
scrapxd-0.1.3.dist-info/licenses/LICENSE
scrapxd-0.1.3.dist-info/METADATA
scrapxd-0.1.3.dist-info/WHEEL
scrapxd-0.1.3.dist-info/top_level.txt
scrapxd-0.1.3.dist-info/RECORD
