Metadata-Version: 2.4
Name: scrapxd
Version: 0.1.3
Summary: A Python library for scraping, analysing and exporting Letterboxd data.
Author-email: Cauã Santos <cauafsantosdev@gmail.com>
License: MIT License
Project-URL: Homepage, https://github.com/cauafsantosdev/scrapxd
Project-URL: Repository, https://github.com/cauafsantosdev/scrapxd
Project-URL: Bug Tracker, https://github.com/cauafsantosdev/scrapxd/issues
Keywords: letterboxd,scraper,web scraping,api,movies
Classifier: Development Status :: 4 - Beta
Classifier: Programming Language :: Python :: 3
Classifier: Operating System :: OS Independent
Classifier: Intended Audience :: Developers
Classifier: Topic :: Software Development :: Libraries :: Python Modules
Classifier: Topic :: Internet :: WWW/HTTP
Requires-Python: >=3.10
License-File: LICENSE
Requires-Dist: requests
Requires-Dist: beautifulsoup4
Requires-Dist: lxml
Requires-Dist: fake-useragent
Requires-Dist: pydantic
Requires-Dist: tenacity
Provides-Extra: test
Requires-Dist: pytest; extra == "test"
Requires-Dist: pytest-cov; extra == "test"
Requires-Dist: pytest-mock; extra == "test"
Provides-Extra: analytics
Requires-Dist: scipy; extra == "analytics"
Provides-Extra: export
Requires-Dist: openpyxl; extra == "export"
Provides-Extra: all
Requires-Dist: scrapxd[test]; extra == "all"
Requires-Dist: scrapxd[analytics]; extra == "all"
Requires-Dist: scrapxd[export]; extra == "all"
Dynamic: license-file
